purdue_af_grafana_iframe/__init__.py
purdue_af_grafana_iframe/_version.py
purdue_af_grafana_iframe-0.1.0.data/data/share/jupyter/labextensions/purdue-af-grafana-iframe/package.json
purdue_af_grafana_iframe-0.1.0.data/data/share/jupyter/labextensions/purdue-af-grafana-iframe/schemas/purdue-af-grafana-iframe/package.json.orig
purdue_af_grafana_iframe-0.1.0.data/data/share/jupyter/labextensions/purdue-af-grafana-iframe/schemas/purdue-af-grafana-iframe/plugin.json
purdue_af_grafana_iframe-0.1.0.data/data/share/jupyter/labextensions/purdue-af-grafana-iframe/static/736.bb45204ee83b3c6ea07a.js
purdue_af_grafana_iframe-0.1.0.data/data/share/jupyter/labextensions/purdue-af-grafana-iframe/static/808.e080290f214674b986fe.js
purdue_af_grafana_iframe-0.1.0.data/data/share/jupyter/labextensions/purdue-af-grafana-iframe/static/remoteEntry.dedc5ba0a7ec98a0a7a4.js
purdue_af_grafana_iframe-0.1.0.data/data/share/jupyter/labextensions/purdue-af-grafana-iframe/static/style.js
purdue_af_grafana_iframe-0.1.0.data/data/share/jupyter/labextensions/purdue-af-grafana-iframe/static/third-party-licenses.json
purdue_af_grafana_iframe-0.1.0.data/data/share/jupyter/labextensions/purdue-af-grafana-iframe/install.json
purdue_af_grafana_iframe-0.1.0.dist-info/METADATA
purdue_af_grafana_iframe-0.1.0.dist-info/WHEEL
purdue_af_grafana_iframe-0.1.0.dist-info/licenses/LICENSE
purdue_af_grafana_iframe-0.1.0.dist-info/RECORD
